vijax/__init__.py
vijax/models/Funana.py
vijax/models/Gaussian.py
vijax/models/InferenceGym.py
vijax/models/Studentt.py
vijax/models/__init__.py
vijax/recipes/__init__.py
vijax/recipes/simplervi.py
vijax/utils/__init__.py
vijax/utils/utils.py
vijax/vardists/Diagonal.py
vijax/vardists/Flows.py
vijax/vardists/Gaussian.py
vijax/vardists/__init__.py
vijax-0.0.3.dist-info/LICENSE
vijax-0.0.3.dist-info/METADATA
vijax-0.0.3.dist-info/WHEEL
vijax-0.0.3.dist-info/top_level.txt
vijax-0.0.3.dist-info/RECORD
