Metadata-Version: 2.1
Name: vijax
Version: 0.0.3
Summary: A JAX library to run VI.
Home-page: https://github.com/abhiagwl/vijax
Author: Abhinav Agrawal
Author-email: agrawal.abhinav1@gmail.com
Classifier: Programming Language :: Python :: 3
Classifier: License :: OSI Approved :: MIT License
Classifier: Operating System :: OS Independent
Requires-Python: >=3.9
License-File: LICENSE
Requires-Dist: jax
Requires-Dist: jaxlib
Requires-Dist: numpyro
Requires-Dist: tensorflow-probability
Requires-Dist: inference-gym
